Workbook

Sheet Inputs
A1: E-Ride Operating Model - Inputs
A2: Edit yellow cells. Other sheets calculate from these assumptions.
A4: Input | B4: Value | C4: Unit / meaning | D4: Notes
A5: Recover fleet assets | B5: 1 | C5: 1=yes, 0=no | D5: Includes motorcycle + backup-battery amortization
A6: Recover development cost | B6: 1 | C6: 1=yes, 0=no | D6: Includes build recovery + ongoing dev retainer
A7: Recover AWS/cloud/API cost | B7: 1 | C7: 1=yes, 0=no | D7: Includes workbook-based cloud/API scaling
A8: Active users | B8: 3750 | C8: users/month | D8: Monthly transacting users
A9: Number of riders / vehicles | B9: 50 | C9: riders | D9: One salaried rider per active vehicle
A10: Rides per user / month | B10: 4 | C10: rides | D10: Actual rides per active user per month
A11: Rides per rider / day | B11: 15 | C11: requested rides | D11: Capacity target
A12: Operating days / month | B12: 26 | C12: days | D12: Monthly operating days
A13: Completion rate | B13: 0.9 | C13: % | D13: Completed rides after cancellations
A14: Average paid trip distance | B14: 6 | C14: km | D14: Fare + energy distance
A15: Average trip duration | B15: 25 | C15: minutes | D15: Paid trip duration
A16: Base fare | B16: 50 | C16: PHP | D16: Includes first 2 km
... A46: Tax / regulatory reserve on revenue | B46: 0.03 | C46: % | D46: Planning reserve

Sheet Scenario_Comparison
A1: Scenario Comparison - Wage Coverage and Profitability
A2: Current setup versus a profitable utilization case that generates fare revenue well above rider wage cost.
A4: Scenario | B4: Active users | C4: Riders | D4: Rides/user/month | E4: Requested rides/rider/day | F4: Completed rides/rider/day | G4: Fare revenue/rider/day | H4: Wage cost/rider/day | I4: Wage coverage | J4: Monthly profit/loss
A5: Current setup | B5: =Inputs!B8 -> 3750 | C5: =Inputs!B9 -> 50 | D5: =Inputs!B10 -> 4 | E5: =Inputs!B11 -> 15 | F5: =Model!B15 -> 10.384615 | G5: =Model!B20 -> 981.34615 | H5: =Inputs!B26*(1+Inputs!B27) -> 799.25 | I5: =G5/H5 -> 1.2278338 | J5: =Model!B32 -> -432749.45
A6: Profitable utilization case | B6: 6000 | C6: 50 | D6: 8 | E6: 20 | F6: =MIN(B6*D6,C6*E6*Inputs!B12)*Inputs!B13/(C6*Inputs!B12) -> 18 | G6: =MIN(B6*D6,C6*E6*Inputs!B12)*Inputs!B13*Model!B9/(C6*Inputs!B12) -> 1701 | H6: =Inputs!B26*(1+Inputs!B27) -> 799.25 | I6: =G6/H6 -> 2.1282452 | J6: =((MIN(B6*D6,C6*E6*Inputs!B12)*Inputs!B13)*Model!B9*Inputs!B24 + B6*Inputs!B25) - (C6*Inputs!B26*Inputs!B12*(1+Inputs!B27) + C6*Inputs!B12*MAX(G6-Inputs!B28,0)*Inputs!B29 + (MIN(B6*D6,C6*E6*Inputs!B12)*Inputs!B13)*Inputs!B14*Inputs!B35*Inputs!B36 + IF(Inputs!B5=1,C6*(Inputs!B30+Inputs!B31)/Inputs!B32,0) + C6*(Inputs!B33+Inputs!B34) + IF(Inputs!B6=1,Inputs!B37/Inputs!B38+Inputs!B39,0) + IF(Inputs!B7=1,Inputs!B40+SUM(MAX(B6*21*5-10000,0)/1000*2.83,MAX(B6*21*2-10000,0)/1000*5,MAX(B6*21*1-10000,0)/1000*5,MAX(B6*21*2-10000,0)/1000*5)*58,0) + Inputs!B41+B6*(Inputs!B42+Inputs!B43) + ((MIN(B6*D6,C6*E6*Inputs!B12)*Inputs!B13)*Model!B9*Inputs!B24+B6*Inputs!B25)*Inputs!B44*Inputs!B45 + ((MIN(B6*D6,C6*E6*Inputs!B12)*Inputs!B13)*Model!B9*Inputs!B24+B6*Inputs!B25)*Inputs!B46) -> 139352.99

Sheet Model
A1: E-Ride Operating Model - Calculations
A2: Core deterministic calculation. This is the Excel fallback for the dashboard.
A4: Metric | B4: Formula / Value | C4: Unit | D4: Meaning
A5: Short distance km | B5: =MIN(MAX(Inputs!B14-Inputs!B17,0),MAX(Inputs!B19-Inputs!B17,0)) -> 4 | C5: km | D5: Charged at regular per-km rate
A6: Long distance km | B6: =MAX(Inputs!B14-Inputs!B19,0) -> 0 | C6: km | D6: Charged at long-distance rate
A7: Charged minutes | B7: =MAX(Inputs!B15-Inputs!B21,0) -> 15 | C7: minutes | D7: Charged beyond base minutes
A8: Fare before discount | B8: =Inputs!B16+B5*Inputs!B18+B6*Inputs!B20+B7*Inputs!B22 -> 105 | C8: PHP/ride | D8: Benchmark fare
A9: Final passenger fare | B9: =B8*(1-Inputs!B23) -> 94.5 | C9: PHP/ride | D9: Passenger fare
A10: Requested demand | B10: =Inputs!B8*Inputs!B10 -> 15000 | C10: rides/month | D10: User demand
A11: Requested fleet capacity | B11: =Inputs!B9*Inputs!B11*Inputs!B12 -> 19500 | C11: rides/month | D11: Fleet capacity
A12: Requested served rides | B12: =MIN(B10,B11) -> 15000 | C12: rides/month | D12: Matched rides
A13: Completed rides | B13: =B12*Inputs!B13 -> 13500 | C13: rides/month | D13: Revenue-generating rides
A14: Completed rides / day | B14: =B13/Inputs!B12 -> 519.23077 | C14: rides/day | D14: Daily completed rides
A15: Completed rides / rider / day | B15: =B13/(Inputs!B9*Inputs!B12) -> 10.384615 | C15: rides/rider/day | D15: Actual utilization
A16: Fare revenue | B16: =B13*B9*Inputs!B24 -> 1275750 | C16: PHP/month | D16: Retained fare revenue
A17: Membership revenue | B17: =Inputs!B8*Inputs!B25 -> 0 | C17: PHP/month | D17: Optional user fees
A18: Total revenue | B18: =B16+B17 -> 1275750 | C18: PHP/month | D18: Total revenue
A19: Rider base payroll | B19: =Inputs!B9*Inputs!B26*Inputs!B12*(1+Inputs!B27) -> 1039025 | C19: PHP/month | D19: Wages plus burden
A20: Gross fare / rider / day | B20: =(B13*B9)/(Inputs!B9*Inputs!B12) -> 981.34615 | C20: PHP/rider/day | D20: Incentive basis
A21: Rider incentives | B21: =Inputs!B9*Inputs!B12*MAX(B20-Inputs!B28,0)*Inputs!B29 -> 0 | C21: PHP/month | D21: Commission above threshold
A22: Electricity | B22: =B13*Inputs!B14*Inputs!B35*Inputs!B36 -> 47385 | C22: PHP/month | D22: Charging cost
A23: Fleet acquisition / amortization | B23: =IF(Inputs!B5=1,Inputs!B9*(Inputs!B30+Inputs!B31)/Inputs!B32,0) -> 104166.67 | C23: PHP/month | D23: Asset recovery switch
A24: Fleet maintenance, insurance, registration | B24: =Inputs!B9*(Inputs!B33+Inputs!B34) -> 100000 | C24: PHP/month | D24: Fleet operating cost
A25: Development build recovery | B25: =IF(Inputs!B6=1,Inputs!B37/Inputs!B38,0) -> 166666.67 | C25: PHP/month | D25: Build recovery switch
A26: Ongoing dev support retainer | B26: =IF(Inputs!B6=1,Inputs!B39,0) -> 55000 | C26: PHP/month | D26: Dev support switch
A27: Cloud / API cost | B27: =IF(Inputs!B7=1,Cloud_Tiers!B8,0) -> 38843.3 | C27: PHP/month | D27: Cloud recovery switch
A28: Operations, support and admin | B28: =Inputs!B41+Inputs!B8*(Inputs!B42+Inputs!B43) -> 146250 | C28: PHP/month | D28: Fixed + user ops
A29: Payment processing | B29: =B18*Inputs!B44*Inputs!B45 -> 11162.812 | C29: PHP/month | D29: Digital payment fee
A30: Tax / regulatory reserve | B30: =B18*Inputs!B46 -> 38272.5 | C30: PHP/month | D30: Revenue reserve
A31: Total cost | B31: =SUM(B19,B21:B29) -> 1708499.4 | C31: PHP/month | D31: Total monthly cost
A32: Monthly profit / loss | B32: =B18-B31 -> -432749.45 | C32: PHP/month | D32: Net result
A33: Required revenue / active user | B33: =B31/Inputs!B8 -> 455.59985 | C33: PHP/user/month | D33: Cost to recover per active user
A34: Revenue / active user | B34: =B18/Inputs!B8 -> 340.2 | C34: PHP/user/month | D34: Current revenue per active user
A35: Profit / active user | B35: =B32/Inputs!B8 -> -115.39985 | C35: PHP/user/month | D35: Net per active user
A36: Cost / completed ride | B36: =B31/B13 -> 126.55551 | C36: PHP/ride | D36: Average cost per ride
A37: Profit / completed ride | B37: =B32/B13 -> -32.055515 | C37: PHP/ride | D37: Average profit per ride
A38: Fleet utilization | B38: =B12/B11 -> 0.76923077 | C38: % | D38: Served requested rides / capacity
A39: Approx. break-even completed rides/month | B39: =IF((B9*Inputs!B24*(1-Inputs!B44*Inputs!B45-Inputs!B46)-Inputs!B14*Inputs!B35*Inputs!B36)>0,(B19+B21+B23+B24+B25+B26+B27+B28)/(B9*Inputs!B24*(1-Inputs!B44*Inputs!B45-Inputs!B46)-Inputs!B14*Inputs!B35*Inputs!B36),"Check fare") -> 18893.703 | C39: rides/month | D39: Approximate target; keeps incentive at current threshold behavior
A40: Approx. break-even completed rides/day | B40: =B39/Inputs!B12 -> 726.68087 | C40: rides/day | D40: Daily target

Sheet Cost_Breakdown
A1: Monthly Cost Breakdown
A2: Cost lines link directly to Model calculations.
A4: Cost category | B4: Monthly PHP | C4: Share of cost | D4: PHP / completed ride
A5: Rider base payroll | B5: =Model!B19 -> 1039025 | C5: =B5/Model!B31 -> 0.60815062 | D5: =B5/Model!B13 -> 76.964815
A6: Rider incentives | B6: =Model!B21 -> 0 | C6: =B6/Model!B31 -> 0 | D6: =B6/Model!B13 -> 0
A7: Electricity | B7: =Model!B22 -> 47385 | C7: =B7/Model!B31 -> 0.027734864 | D7: =B7/Model!B13 -> 3.51
A8: Fleet acquisition / amortization | B8: =Model!B23 -> 104166.67 | C8: =B8/Model!B31 -> 0.060969681 | D8: =B8/Model!B13 -> 7.7160494
A9: Fleet maintenance, insurance, registration | B9: =Model!B24 -> 100000 | C9: =B9/Model!B31 -> 0.058530894 | D9: =B9/Model!B13 -> 7.4074074
A10: Development build recovery | B10: =Model!B25 -> 166666.67 | C10: =B10/Model!B31 -> 0.09755149 | D10: =B10/Model!B13 -> 12.345679
A11: Ongoing dev support retainer | B11: =Model!B26 -> 55000 | C11: =B11/Model!B31 -> 0.032191992 | D11: =B11/Model!B13 -> 4.0740741
A12: Cloud / API cost | B12: =Model!B27 -> 38843.3 | C12: =B12/Model!B31 -> 0.022735331 | D12: =B12/Model!B13 -> 2.8772815
A13: Operations, support and admin | B13: =Model!B28 -> 146250 | C13: =B13/Model!B31 -> 0.085601433 | D13: =B13/Model!B13 -> 10.833333
A14: Payment processing | B14: =Model!B29 -> 11162.812 | C14: =B14/Model!B31 -> 0.006533694 | D14: =B14/Model!B13 -> 0.826875
A15: Tax / regulatory reserve | B15: =Model!B30 -> 38272.5 | C15: =B15/Model!B31 -> 0.022401236 | D15: =B15/Model!B13 -> 2.835

Sheet Cloud_Tiers
A1: AWS / Cloud and API Cost Tiers
A2: Uses the workbook-based Google Maps/API scaling plus POC baseline.
A4: Tier | B4: Estimated monthly cloud/API cost | C4: Active users | D4: Cost / active user
A5: POC pilot | B5: =Inputs!B40+SUM(MAX(C5*21*5-10000,0)/1000*2.83,MAX(C5*21*2-10000,0)/1000*5,MAX(C5*21*1-10000,0)/1000*5,MAX(C5*21*2-10000,0)/1000*5)*58 -> 1500 | C5: 20 | D5: =B5/C5 -> 75
A6: Small internal launch | B6: =Inputs!B40+SUM(MAX(C6*21*5-10000,0)/1000*2.83,MAX(C6*21*2-10000,0)/1000*5,MAX(C6*21*1-10000,0)/1000*5,MAX(C6*21*2-10000,0)/1000*5)*58 -> 1582.07 | C6: 100 | D6: =B6/C6 -> 15.8207
A7: Campus/barangay launch | B7: =Inputs!B40+SUM(MAX(C7*21*5-10000,0)/1000*2.83,MAX(C7*21*2-10000,0)/1000*5,MAX(C7*21*1-10000,0)/1000*5,MAX(C7*21*2-10000,0)/1000*5)*58 -> 15000.95 | C7: 500 | D7: =B7/C7 -> 30.0019
A8: Early city launch | B8: =Inputs!B40+SUM(MAX(C8*21*5-10000,0)/1000*2.83,MAX(C8*21*2-10000,0)/1000*5,MAX(C8*21*1-10000,0)/1000*5,MAX(C8*21*2-10000,0)/1000*5)*58 -> 38843.3 | C8: 1000 | D8: =B8/C8 -> 38.8433
A9: Current scenario | B9: =Inputs!B40+SUM(MAX(C9*21*5-10000,0)/1000*2.83,MAX(C9*21*2-10000,0)/1000*5,MAX(C9*21*1-10000,0)/1000*5,MAX(C9*21*2-10000,0)/1000*5)*58 -> 169976.22 | C9: =Inputs!B8 -> 3750 | D9: =B9/C9 -> 45.326993
A10: Dense launch | B10: =Inputs!B40+SUM(MAX(C10*21*5-10000,0)/1000*2.83,MAX(C10*21*2-10000,0)/1000*5,MAX(C10*21*1-10000,0)/1000*5,MAX(C10*21*2-10000,0)/1000*5)*58 -> 229582.1 | C10: 5000 | D10: =B10/C10 -> 45.91642
A11: City scale | B11: =Inputs!B40+SUM(MAX(C11*21*5-10000,0)/1000*2.83,MAX(C11*21*2-10000,0)/1000*5,MAX(C11*21*1-10000,0)/1000*5,MAX(C11*21*2-10000,0)/1000*5)*58 -> 468005.6 | C11: 10000 | D11: =B11/C11 -> 46.80056
A12: Metro scale stress test | B12: =Inputs!B40+SUM(MAX(C12*21*5-10000,0)/1000*2.83,MAX(C12*21*2-10000,0)/1000*5,MAX(C12*21*1-10000,0)/1000*5,MAX(C12*21*2-10000,0)/1000*5)*58 -> 1183276.1 | C12: 25000 | D12: =B12/C12 -> 47.331044

Sheet Dev_Budget
A1: Development Budget Allocation
A2: Default allocation sums to PHP 1,000,000 and scales with the editable build budget.
A4: Role | B4: 6-month allocation | C4: Monthly allocation | D4: Share
A5: Lead full-stack developer / PM | B5: =330000/1000000*Inputs!B37 -> 330000 | C5: =B5/6 -> 55000 | D5: =B5/SUM($B$5:$B$11) -> 0.33
A6: Backend developer | B6: =180000/1000000*Inputs!B37 -> 180000 | C6: =B6/6 -> 30000 | D6: =B6/SUM($B$5:$B$11) -> 0.18
A7: Frontend/mobile developer | B7: =140000/1000000*Inputs!B37 -> 140000 | C7: =B7/6 -> 23333.333 | D7: =B7/SUM($B$5:$B$11) -> 0.14
A8: Cloud / DevOps engineer | B8: =120000/1000000*Inputs!B37 -> 120000 | C8: =B8/6 -> 20000 | D8: =B8/SUM($B$5:$B$11) -> 0.12
A9: QA and release support | B9: =90000/1000000*Inputs!B37 -> 90000 | C9: =B9/6 -> 15000 | D9: =B9/SUM($B$5:$B$11) -> 0.09
A10: Product / client coordination | B10: =80000/1000000*Inputs!B37 -> 80000 | C10: =B10/6 -> 13333.333 | D10: =B10/SUM($B$5:$B$11) -> 0.08
A11: UI/UX and presentation support | B11: =60000/1000000*Inputs!B37 -> 60000 | C11: =B11/6 -> 10000 | D11: =B11/SUM($B$5:$B$11) -> 0.06
A12: Total | B12: =SUM(B5:B11) -> 1000000 | C12: =SUM(C5:C11) -> 166666.67 | D12: =SUM(D5:D11) -> 1

Sheet Notes
A1: Model Notes
A2: Use this workbook if the dashboard is unavailable.
A4: Topic | B4: Note
A5: Purpose | B5: Answer how much E-Ride must earn per user and how many completed rides/day are needed to maintain service.
A6: Toggles | B6: Inputs rows 5-7 control whether fleet assets, development cost, and cloud/API cost are recovered in monthly profit.
A7: Cloud basis | B7: POC baseline is PHP 1,500. Growth uses 21 days, PHP 58/USD, 10,000 free monthly events per priced API, and per-user daily API ratios from the Dev Costing Foundation workbook.
A8: Fare basis | B8: Fare follows base + distance + time, then applies the E-Ride electric discount.
A9: Break-even caution | B9: Break-even rides/day is an approximation because incentives can change once gross fare/rider/day crosses the threshold.
